examplePackage/__init__.py
examplePackage/example.py
ThisIsAnExamplePackage3-0.0.1.dist-info/LICENSE
ThisIsAnExamplePackage3-0.0.1.dist-info/METADATA
ThisIsAnExamplePackage3-0.0.1.dist-info/WHEEL
ThisIsAnExamplePackage3-0.0.1.dist-info/top_level.txt
ThisIsAnExamplePackage3-0.0.1.dist-info/RECORD
