Metadata-Version: 2.1
Name: ThisIsAnExamplePackage3
Version: 0.0.1
Summary: UNKNOWN
Home-page: UNKNOWN
License: UNKNOWN
Platform: UNKNOWN
License-File: LICENSE
Requires-Dist: requests
Requires-Dist: importlib-metadata ; python_version == "3.8"
